wagtail_association_panel/__init__.py
wagtail_association_panel/apps.py
wagtail_association_panel/association_panel.py
wagtail_association_panel/templates/wagtail_association_panel/association_panel.html
wagtail_association_panel/templates/wagtail_association_panel/association_panel_child.html
wagtail_association_panel-4.1.0.dist-info/AUTHORS.txt
wagtail_association_panel-4.1.0.dist-info/LICENSE.txt
wagtail_association_panel-4.1.0.dist-info/METADATA
wagtail_association_panel-4.1.0.dist-info/WHEEL
wagtail_association_panel-4.1.0.dist-info/top_level.txt
wagtail_association_panel-4.1.0.dist-info/zip-safe
wagtail_association_panel-4.1.0.dist-info/RECORD
